pytest_failure_tracker/__init__.py
pytest_failure_tracker/plugin.py
pytest_failure_tracker-0.2.3.dist-info/LICENSE
pytest_failure_tracker-0.2.3.dist-info/METADATA
pytest_failure_tracker-0.2.3.dist-info/WHEEL
pytest_failure_tracker-0.2.3.dist-info/entry_points.txt
pytest_failure_tracker-0.2.3.dist-info/top_level.txt
pytest_failure_tracker-0.2.3.dist-info/RECORD
