Metadata-Version: 2.1
Name: pytest-failure-tracker
Version: 0.2.3
Summary: A pytest plugin for tracking test failures over multiple runs
Home-page: https://github.com/izikeros/pytest-failure-tracker
Author: Krystian Safjan
Author-email: ksafjan@gmail.com
Classifier: Framework :: Pytest
Classifier: Programming Language :: Python :: 3
Classifier: Programming Language :: Python :: 3.7
Classifier: Programming Language :: Python :: 3.8
Classifier: Programming Language :: Python :: 3.9
Classifier: Programming Language :: Python :: 3.10
Classifier: Programming Language :: Python :: 3.11
Classifier: Programming Language :: Python :: 3.12
Classifier: Programming Language :: Python :: 3 :: Only
Classifier: License :: OSI Approved :: MIT License
Classifier: Operating System :: OS Independent
Requires-Python: >=3.7
License-File: LICENSE
Requires-Dist: pytest >=6.0.0
